viewtools/__init__.py
viewtools/__main__.py
viewtools/_logging.py
viewtools/api/__init__.py
viewtools/api/rearrange.py
viewtools/cli/__init__.py
viewtools/cli/main.py
viewtools/cli/rearrange_bedframe.py
viewtools/cli/rearrange_genome.py
viewtools/core/__init__.py
viewtools/core/utils.py
viewtools-0.1.2.dist-info/METADATA
viewtools-0.1.2.dist-info/WHEEL
viewtools-0.1.2.dist-info/entry_points.txt
viewtools-0.1.2.dist-info/licenses/LICENSE
viewtools-0.1.2.dist-info/RECORD
