Metadata-Version: 2.4
Name: viewtools
Version: 0.1.2
Summary: Tools for working with genomic intervals and sequences
Project-URL: Homepage, https://github.com/yourusername/viewtools
Project-URL: Repository, https://github.com/yourusername/viewtools
Project-URL: Issues, https://github.com/yourusername/viewtools/issues
Author-email: Your Name <your.email@example.com>
License: MIT
License-File: LICENSE
Classifier: Development Status :: 4 - Beta
Classifier: Intended Audience :: Science/Research
Classifier: License :: OSI Approved :: MIT License
Classifier: Operating System :: OS Independent
Classifier: Programming Language :: Python :: 3
Classifier: Programming Language :: Python :: 3.8
Classifier: Programming Language :: Python :: 3.9
Classifier: Programming Language :: Python :: 3.10
Classifier: Programming Language :: Python :: 3.11
Classifier: Programming Language :: Python :: 3.12
Classifier: Topic :: Scientific/Engineering :: Bio-Informatics
Requires-Python: >=3.8
Requires-Dist: bioframe
Requires-Dist: biopython
Requires-Dist: click
Requires-Dist: pandas
Provides-Extra: dev
Requires-Dist: black; extra == 'dev'
Requires-Dist: linkify-it-py; extra == 'dev'
Requires-Dist: myst-parser; extra == 'dev'
Requires-Dist: pytest; extra == 'dev'
Requires-Dist: pytest-cov; extra == 'dev'
Requires-Dist: ruff; extra == 'dev'
Requires-Dist: sphinx-autobuild; extra == 'dev'
Requires-Dist: sphinx-autodoc-typehints; extra == 'dev'
Requires-Dist: sphinx-rtd-theme; extra == 'dev'
Requires-Dist: sphinx>=4.0; extra == 'dev'
